Workbook

Sheet Testfälle
A1: id | B1: konto | C1: text | D1: falltyp | E1: skill | F1: tool | G1: Bezugsgruppe | H1: konto-ID | I1: branche | J1: quellenbezug
A2: SP-001 | B2: Surfers Pottery | C2: Fürs Töpfern hätte ich gern einen Termin. | D2: Positiv | E2: calendar | F2: get_user_info ODER get_event_types ODER get_available_slots | G2: SP-G001 | H2: 6e973b68-abb6-4470-b341-2f2377da93dd | I2: Handwerk / Töpferei | J2: Kalender-Skill: neue Buchung
A3: SP-002 | B3: Surfers Pottery | C3: Den Töpfertermin verschieben wir als Idee auf später. | D3: Negativ | E3: none | F3: keines der Zielwerkzeuge | G3: SP-G001 | H3: 6e973b68-abb6-4470-b341-2f2377da93dd | I3: Handwerk / Töpferei | J3: Kalender-Skill: neue Buchung
A4: SP-003 | B4: Surfers Pottery | C4: Ich würde das gern vor Ort besprechen. Können wir dafür einen Termin festlegen? | D4: Positiv | E4: calendar | F4: get_user_info ODER get_event_types ODER get_available_slots | G4: SP-G001 | H4: 6e973b68-abb6-4470-b341-2f2377da93dd | I4: Handwerk / Töpferei | J4: Kalender-Skill: neue Buchung
A5: SP-004 | B5: Surfers Pottery | C5: Morgen Nachmittag meinte ich meine private Verabredung. Bei Ihnen brauche ich nichts. | D5: Negativ | E5: none | F5: keines der Zielwerkzeuge | G5: SP-G002 | H5: 6e973b68-abb6-4470-b341-2f2377da93dd | I5: Handwerk / Töpferei | J5: Kalender-Skill: Verfügbarkeit
A6: SP-005 | B6: Surfers Pottery | C6: Ich habe morgen nach der Arbeit Zeit und würde gern zu Ihnen kommen. Schauen Sie mal, ob zwischen vier und sechs noch etwas frei ist. | D6: Positiv | E6: calendar | F6: get_user_info ODER get_event_types ODER get_available_slots | G6: SP-G002 | H6: 6e973b68-abb6-4470-b341-2f2377da93dd | I6: Handwerk / Töpferei | J6: Kalender-Skill: Verfügbarkeit
A7: SP-006 | B7: Surfers Pottery | C7: Ich kann morgen erst nachmittags. Würden Sie nachsehen, ob dann ein Termin zum Töpfern frei ist? | D7: Positiv | E7: calendar | F7: get_user_info ODER get_event_types ODER get_available_slots | G7: SP-G002 | H7: 6e973b68-abb6-4470-b341-2f2377da93dd | I7: Handwerk / Töpferei | J7: Kalender-Skill: Verfügbarkeit
A8: SP-007 | B8: Surfers Pottery | C8: Samstag oder Sonntag könnte ich kommen. Welche freien Termine finden Sie? | D8: Positiv | E8: calendar | F8: get_user_info ODER get_event_types ODER get_available_slots | G8: SP-G003 | H8: 6e973b68-abb6-4470-b341-2f2377da93dd | I8: Handwerk / Töpferei | J8: Kalender-Skill: Verfügbarkeit
A9: SP-008 | B9: Surfers Pottery | C9: Wann könnte ich am Wochenende zum Töpfern vorbeilaufen? Bitte prüfen Sie freie Termine. | D9: Positiv | E9: calendar | F9: get_user_info ODER get_event_types ODER get_available_slots | G9: SP-G003 | H9: 6e973b68-abb6-4470-b341-2f2377da93dd | I9: Handwerk / Töpferei | J9: Kalender-Skill: Verfügbarkeit
A10: SP-009 | B10: Surfers Pottery | C10: Am Wochenende wollte ich töpfern, aber inzwischen hat sich Besuch angekündigt. Deshalb möchte ich keinen Termin mehr suchen lassen. Die Planung für einen späteren Besuch übernehme ich erst einmal selbst. | D10: Negativ | E10: none | F10: keines der Zielwerkzeuge | G10: SP-G003 | H10: 6e973b68-abb6-4470-b341-2f2377da93dd | I10: Handwerk / Töpferei | J10: Kalender-Skill: Verfügbarkeit
A11: SP-010 | B11: Surfers Pottery | C11: Meine Freundin würde mitmachen. Wir möchten gemeinsam töpfern und dafür einen Termin buchen, haben aber noch keinen bestimmten Tag im Kopf. | D11: Positiv | E11: calendar | F11: get_user_info ODER get_event_types ODER get_available_slots | G11: SP-G004 | H11: 6e973b68-abb6-4470-b341-2f2377da93dd | I11: Handwerk / Töpferei | J11: Kalender-Skill: neue Buchung
A12: SP-011 | B12: Surfers Pottery | C12: Eine gemeinsame Buchung ist noch nicht beschlossen. | D12: Negativ | E12: none | F12: keines der Zielwerkzeuge | G12: SP-G004 | H12: 6e973b68-abb6-4470-b341-2f2377da93dd | I12: Handwerk / Töpferei | J12: Kalender-Skill: neue Buchung
... A301: PI-021 | B301: PIABO | C301: Ich höre unterwegs gern Podcasts und habe gesehen, dass PIABO dieses Thema aufführt. Welche Informationen gibt es zu eurem Podcast und seinen Inhalten? | D301: Positiv | E301: knowledge-base | F301: faq_search | G301: PI-G007 | H301: 903a47ec-4d5b-481a-947a-4156b23059d9 | I301: PR / Kommunikation | J301: FAQ-Thema: Podcast

Sheet Übersicht
A1: Spalte | B1: Beschreibung
A2: id | B2: Eindeutige Kennung des Testitems
A3: konto | B3: Name des getesteten Agentenkontos
A4: text | B4: Testäußerung
A5: falltyp | B5: Positiv: Ein Ziel-Skill soll aktiviert werden. Negativ: Keiner der Ziel-Skills soll aktiviert werden.
A6: skill | B6: Erwarteter Skill: calendar, knowledge-base, forwarding oder none
A7: tool | B7: Erwartetes Werkzeug gemäß der Kontokonfiguration aus dem Playground-Export (JSON)
A8: Bezugsgruppe | B8: Ursprüngliche Gruppierung von Items mit demselben Grundanliegen. Nach der manuellen Überarbeitung ist die Zuordnung teilweise nicht mehr zutreffend.
A9: konto-ID | B9: Eindeutige Agenten-ID aus dem Playground
A10: branche | B10: Branche des Unternehmens
A11: quellenbezug | B11: Grundlage des Items, z. B. FAQ-Thema, Dokumentabschnitt oder Weiterleitungsanweisung

Sheet KI_Übersicht
A2: Testumfang nach Konto
A4: Konto | B4: Kalender positiv | C4: Wissen positiv | D4: Weiterleitung positiv | E4: Negativ | F4: Gesamt
A5: Surfers Pottery | B5: =COUNTIFS('Testfälle'!$B$2:$B$301,A5,'Testfälle'!$E$2:$E$301,"calendar") -> 14 | C5: =COUNTIFS('Testfälle'!$B$2:$B$301,A5,'Testfälle'!$E$2:$E$301,"knowledge-base") -> 12 | D5: =COUNTIFS('Testfälle'!$B$2:$B$301,A5,'Testfälle'!$E$2:$E$301,"forwarding") -> 16 | E5: =COUNTIFS('Testfälle'!$B$2:$B$301,A5,'Testfälle'!$D$2:$D$301,"Negativ") -> 21 | F5: =SUM(B5:E5) -> 63
A6: Amazon Business | B6: =COUNTIFS('Testfälle'!$B$2:$B$301,A6,'Testfälle'!$E$2:$E$301,"calendar") -> 0 | C6: =COUNTIFS('Testfälle'!$B$2:$B$301,A6,'Testfälle'!$E$2:$E$301,"knowledge-base") -> 8 | D6: =COUNTIFS('Testfälle'!$B$2:$B$301,A6,'Testfälle'!$E$2:$E$301,"forwarding") -> 0 | E6: =COUNTIFS('Testfälle'!$B$2:$B$301,A6,'Testfälle'!$D$2:$D$301,"Negativ") -> 4 | F6: =SUM(B6:E6) -> 12
A7: E-Commerce | B7: =COUNTIFS('Testfälle'!$B$2:$B$301,A7,'Testfälle'!$E$2:$E$301,"calendar") -> 0 | C7: =COUNTIFS('Testfälle'!$B$2:$B$301,A7,'Testfälle'!$E$2:$E$301,"knowledge-base") -> 8 | D7: =COUNTIFS('Testfälle'!$B$2:$B$301,A7,'Testfälle'!$E$2:$E$301,"forwarding") -> 0 | E7: =COUNTIFS('Testfälle'!$B$2:$B$301,A7,'Testfälle'!$D$2:$D$301,"Negativ") -> 4 | F7: =SUM(B7:E7) -> 12
A8: Hausheld (Kopie) | B8: =COUNTIFS('Testfälle'!$B$2:$B$301,A8,'Testfälle'!$E$2:$E$301,"calendar") -> 0 | C8: =COUNTIFS('Testfälle'!$B$2:$B$301,A8,'Testfälle'!$E$2:$E$301,"knowledge-base") -> 14 | D8: =COUNTIFS('Testfälle'!$B$2:$B$301,A8,'Testfälle'!$E$2:$E$301,"forwarding") -> 24 | E8: =COUNTIFS('Testfälle'!$B$2:$B$301,A8,'Testfälle'!$D$2:$D$301,"Negativ") -> 19 | F8: =SUM(B8:E8) -> 57
A9: Pedalino Fahrradhersteller – Bestellung aufnehmen | B9: =COUNTIFS('Testfälle'!$B$2:$B$301,A9,'Testfälle'!$E$2:$E$301,"calendar") -> 0 | C9: =COUNTIFS('Testfälle'!$B$2:$B$301,A9,'Testfälle'!$E$2:$E$301,"knowledge-base") -> 10 | D9: =COUNTIFS('Testfälle'!$B$2:$B$301,A9,'Testfälle'!$E$2:$E$301,"forwarding") -> 0 | E9: =COUNTIFS('Testfälle'!$B$2:$B$301,A9,'Testfälle'!$D$2:$D$301,"Negativ") -> 5 | F9: =SUM(B9:E9) -> 15
A10: ZEG – Test Agent | B10: =COUNTIFS('Testfälle'!$B$2:$B$301,A10,'Testfälle'!$E$2:$E$301,"calendar") -> 14 | C10: =COUNTIFS('Testfälle'!$B$2:$B$301,A10,'Testfälle'!$E$2:$E$301,"knowledge-base") -> 10 | D10: =COUNTIFS('Testfälle'!$B$2:$B$301,A10,'Testfälle'!$E$2:$E$301,"forwarding") -> 0 | E10: =COUNTIFS('Testfälle'!$B$2:$B$301,A10,'Testfälle'!$D$2:$D$301,"Negativ") -> 12 | F10: =SUM(B10:E10) -> 36
A11: Surfers Immobilien | B11: =COUNTIFS('Testfälle'!$B$2:$B$301,A11,'Testfälle'!$E$2:$E$301,"calendar") -> 14 | C11: =COUNTIFS('Testfälle'!$B$2:$B$301,A11,'Testfälle'!$E$2:$E$301,"knowledge-base") -> 0 | D11: =COUNTIFS('Testfälle'!$B$2:$B$301,A11,'Testfälle'!$E$2:$E$301,"forwarding") -> 0 | E11: =COUNTIFS('Testfälle'!$B$2:$B$301,A11,'Testfälle'!$D$2:$D$301,"Negativ") -> 7 | F11: =SUM(B11:E11) -> 21
A12: Schreinerei Surfers | B12: =COUNTIFS('Testfälle'!$B$2:$B$301,A12,'Testfälle'!$E$2:$E$301,"calendar") -> 14 | C12: =COUNTIFS('Testfälle'!$B$2:$B$301,A12,'Testfälle'!$E$2:$E$301,"knowledge-base") -> 0 | D12: =COUNTIFS('Testfälle'!$B$2:$B$301,A12,'Testfälle'!$E$2:$E$301,"forwarding") -> 0 | E12: =COUNTIFS('Testfälle'!$B$2:$B$301,A12,'Testfälle'!$D$2:$D$301,"Negativ") -> 7 | F12: =SUM(B12:E12) -> 21
A13: Surfers Medical | B13: =COUNTIFS('Testfälle'!$B$2:$B$301,A13,'Testfälle'!$E$2:$E$301,"calendar") -> 14 | C13: =COUNTIFS('Testfälle'!$B$2:$B$301,A13,'Testfälle'!$E$2:$E$301,"knowledge-base") -> 0 | D13: =COUNTIFS('Testfälle'!$B$2:$B$301,A13,'Testfälle'!$E$2:$E$301,"forwarding") -> 0 | E13: =COUNTIFS('Testfälle'!$B$2:$B$301,A13,'Testfälle'!$D$2:$D$301,"Negativ") -> 7 | F13: =SUM(B13:E13) -> 21
A14: Schornsteinfeger – Outbound Beispiel | B14: =COUNTIFS('Testfälle'!$B$2:$B$301,A14,'Testfälle'!$E$2:$E$301,"calendar") -> 0 | C14: =COUNTIFS('Testfälle'!$B$2:$B$301,A14,'Testfälle'!$E$2:$E$301,"knowledge-base") -> 14 | D14: =COUNTIFS('Testfälle'!$B$2:$B$301,A14,'Testfälle'!$E$2:$E$301,"forwarding") -> 0 | E14: =COUNTIFS('Testfälle'!$B$2:$B$301,A14,'Testfälle'!$D$2:$D$301,"Negativ") -> 7 | F14: =SUM(B14:E14) -> 21
A15: PIABO | B15: =COUNTIFS('Testfälle'!$B$2:$B$301,A15,'Testfälle'!$E$2:$E$301,"calendar") -> 0 | C15: =COUNTIFS('Testfälle'!$B$2:$B$301,A15,'Testfälle'!$E$2:$E$301,"knowledge-base") -> 14 | D15: =COUNTIFS('Testfälle'!$B$2:$B$301,A15,'Testfälle'!$E$2:$E$301,"forwarding") -> 0 | E15: =COUNTIFS('Testfälle'!$B$2:$B$301,A15,'Testfälle'!$D$2:$D$301,"Negativ") -> 7 | F15: =SUM(B15:E15) -> 21
A16: Gesamt | B16: =SUM(B5:B15) -> 70 | C16: =SUM(C5:C15) -> 90 | D16: =SUM(D5:D15) -> 40 | E16: =SUM(E5:E15) -> 100 | F16: =SUM(F5:F15) -> 300
A19: Länge der Testäußerungen | B19: Falltyp | C19: Anzahl | D19: Ø Wörter | E19: Bis 10 Wörter | F19: Ab 26 Wörter
A20: Kalender | B20: Positiv | C20: 70 | D20: 17.3 | E20: 20 | F20: 21
A21: Kalender | B21: Negativ | C21: 35 | D21: 16.4 | E21: 12 | F21: 11
A22: Wissensdatenbank | B22: Positiv | C22: 90 | D22: 16.7 | E22: 30 | F22: 30
A23: Wissensdatenbank | B23: Negativ | C23: 45 | D23: 15.4 | E23: 17 | F23: 13
A24: Weiterleitung | B24: Positiv | C24: 40 | D24: 16.3 | E24: 15 | F24: 13
A25: Weiterleitung | B25: Negativ | C25: 20 | D25: 15.8 | E25: 7 | F25: 6
A28: Bewertungsgrundlage
A29: 200 positive Fälle und 100 Negativfälle. Ziel-Skills: calendar, knowledge-base und forwarding.
A30: Negativ bedeutet: Keiner der drei Ziel-Skills soll aktiviert werden. Erst eine falsche Aktivierung ist ein False Positive.
A31: Callback, Outbound, Zusammenfassungs-SMS und Gesprächsende werden nicht als Zielwerkzeuge bewertet.
A32: Nur die Testäußerung an den Agenten geben. Konto-ID zur Auswahl der Konfiguration nutzen; Labels und Begründungen nicht mitsenden.
A33: Jeden Fall mit frischem Gesprächszustand starten. Bezugsgruppen sind Vergleichspaare, keine aufeinanderfolgenden Gesprächsbeiträge.
A34: Relative Datumsangaben beziehen sich auf das Testdatum. Für Wiederholungen dasselbe Referenzdatum und Europe/Berlin verwenden.
A35: Satzlängen sind gemischt. Die Längenübersicht dokumentiert den Auslieferungsstand; sie ist keine Wirksamkeitsmessung.
A36: Die drei Konten ohne gelieferten Dokumentinhalt erhalten nur Kalenderfälle. Es werden keine Terminarten oder freien Slots behauptet.

Sheet KI_Konten und Prüfregeln
A1: Kürzel | B1: Konto | C1: Konto-ID | D1: Aktive Ziel-Skills | E1: Wissensquellen im Export | F1: Für die Testfälle verwendet | G1: Einschränkung / Abgrenzung
A2: SP | B2: Surfers Pottery | C2: 6e973b68-abb6-4470-b341-2f2377da93dd | D2: knowledge-base, forwarding, calendar | E2: FAQ-Themen: Kursangebot, Zielgruppe, Gruppengröße, Material und Brennen, Ablauf, Öffnungszeiten, Adresse, Anfahrt und Parken, Buchung und Kontakt, Dauer der Kurse, Abholung der Werke, Gutscheine, Teambuilding und Events, Bewertungen, Altersbeschränkung, Mitbringen, Fehler und Perfektion, Corona und Hygiene, Zufriedenheitsgarantie, Social Media Dokumente: Fiktive Produktliste: Beispielsortiment und Preise für handgefertigte Keramik im Pottery Laden; Surfers Pottery Studio Handbook: Equipment, Clay Types & Glazes Overview (Spring 2026 Edition) | F2: Konfiguration; gelieferte Produktliste mit 52 Produkten; Studiohandbuch, Abschnitte 1.2, 3, 4.1 und 5. | G2: Widerspruch zwischen Unternehmensbeschreibung (Krefeld) und Handbuch (Westerland): keine Orts-/Teamfragen. Keine Kalender-Termintypen geliefert.
A3: AM | B3: Amazon Business | C3: 5df72d23-ccb8-4c0c-b89c-9a7f0c9314bb | D3: knowledge-base | E3: FAQ-Themen: Genehmigungsworkflows, Kontakt, Systemintegration, Öffnungszeiten, Adresse, Dienstleistungen, Integration, Konto-Einstellungen, Training, Support, Onboarding, Compliance, Mobile App, Ressourcen, Kundengröße, Preisgestaltung, Datenschutz, Bestellungen, Berichte, Zahlungsarten Keine Dokumente | F3: FAQ-Themen aus dem Konfigurationsexport; keine Prüfung von Antwortinhalten. | G3: Callback und Outbound ausgeschlossen.
A4: EC | B4: E-Commerce | C4: 323389d6-e65c-42c6-81c9-eb41524068e7 | D4: knowledge-base | E4: FAQ-Themen: Genehmigungsworkflows, Kontakt, Systemintegration, Öffnungszeiten, Adresse, Dienstleistungen, Integration, Konto-Einstellungen, Training, Support, Onboarding, Compliance, Mobile App, Ressourcen, Kundengröße, Preisgestaltung, Datenschutz, Bestellungen, Berichte, Zahlungsarten Keine Dokumente | F4: FAQ-Themen aus dem Konfigurationsexport; keine Prüfung von Antwortinhalten. | G4: Eigenes Konto, getrennt von Amazon Business. Zusammenfassungs-SMS ausgeschlossen; keine Negativfälle mit eindeutiger Verabschiedung.
A5: HH | B5: Hausheld (Kopie) | C5: b1c085b9-c6a6-4af9-8572-af63747d06f8 | D5: knowledge-base, forwarding | E5: FAQ-Themen: Adresse, Dienstleistungen, Smart Meter Rollout, Datenschutz und Sicherheit, Kontaktaufnahme Dokumente: Vorteile intelligenter Messsysteme: Transparenz, Kostenkontrolle und flexible Stromtarife; Anleitung zur Anmeldung im Portal und Zugangsdaten nach Anbieterwechsel | F5: Konfiguration mit 5 Weiterleitungsthemen; FAQ-Themen; Dokument Vorteile eines intelligenten Messsystems einschließlich Einbauprozess. | G5: Separates Dokument zu Portalregistrierung nach Anbieterwechsel fehlt. Einbauprozess nicht mit diesem fehlenden Dokument gleichsetzen.
A6: PD | B6: Pedalino Fahrradhersteller – Bestellung aufnehmen | C6: 10716ba9-cb6a-4823-976c-ba7e36eff4a0 | D6: knowledge-base | E6: FAQ-Themen: Alter Laufrad, Retour, Lieferzeit, TÜV, Fahrradgröße, Öffnungszeiten, Probefahrtt, Finanzierung, Beratungstermin, Zahlungsarten, Beratung, Parkplätze Keine Dokumente | F6: FAQ-Themen aus dem Konfigurationsexport; keine Prüfung von Antwortinhalten. | G6: Callback und Outbound ausgeschlossen.
A7: ZE | B7: ZEG – Test Agent | C7: 4379e986-dc93-4dda-a6eb-c5b8742e9ed0 | D7: knowledge-base, calendar | E7: FAQ-Themen: Alter Laufrad, Retour, Lieferzeit, TÜV, Fahrradgröße, Öffnungszeiten, Probefahrtt, Finanzierung, Beratungstermin, Zahlungsarten, Beratung, Parkplätze Keine Dokumente | F7: FAQ-Themen aus dem Konfigurationsexport; keine Prüfung von Antwortinhalten. | G7: Kalender-Termintypen fehlen. Probefahrt und Beratungstermin als FAQ-Regeln, nicht als nachgewiesene Kalender-Termintypen.
A8: IM | B8: Surfers Immobilien | C8: 52177bab-62c0-474a-87b4-b8a355ba0fb4 | D8: knowledge-base, calendar | E8: Keine FAQ-Themen Dokumente: Surfers Immobilien eG: Interne Wissensdatenbank für Telefonservice & Mitgliedschaftsinfos | F8: Nur Kalenderkonfiguration; keine Wissensfragen. | G8: Verknüpftes Dokument und Kalender-Termintypen nicht geliefert. Nur allgemeine neue Terminvereinbarung und Verfügbarkeit.
A9: SC | B9: Schreinerei Surfers | C9: 01f5d0c6-e1f4-432f-ad89-94014562762a | D9: knowledge-base, calendar | E9: Keine FAQ-Themen Dokumente: Interne Wissensdatenbank: Telefonservice & Leistungen der Schreinerei Surfers Düsseldorf | F9: Nur Kalenderkonfiguration; keine Wissensfragen. | G9: Verknüpftes Dokument und Kalender-Termintypen nicht geliefert. Nur allgemeine neue Terminvereinbarung und Verfügbarkeit.
A10: ME | B10: Surfers Medical | C10: 833dfeb1-1c9a-4822-a7ea-10edf73f8732 | D10: knowledge-base, calendar | E10: Keine FAQ-Themen Dokumente: Surfers Medical: Interne Wissensdatenbank für den telefonischen Praxisservice und Patienteninformation | F10: Nur Kalenderkonfiguration; keine Wissensfragen. | G10: Verknüpftes Dokument und Kalender-Termintypen nicht geliefert. Nur allgemeine neue Terminvereinbarung und Verfügbarkeit.
A11: CH | B11: Schornsteinfeger – Outbound Beispiel | C11: 19813ae8-1923-4a5b-aad4-2b6bf88fb464 | D11: knowledge-base | E11: FAQ-Themen: Leistungen, Einsatzort, Kurzfristige Termin, Anwesenheit vor Ort, Dauer eines Besuches, Kosten, Unterlagen / Dokumentation, Emissionsmessung, Vorbereitungen, Beratung Keine Dokumente | F11: FAQ-Themen aus dem Konfigurationsexport; keine Prüfung von Antwortinhalten. | G11: Outbound ist initial geladen, wird aber nicht bewertet. „Kurzfristige Termin“ ist ein FAQ-Thema, kein Kalenderzugang.
A12: PI | B12: PIABO | C12: 903a47ec-4d5b-481a-947a-4156b23059d9 | D12: knowledge-base | E12: FAQ-Themen: Leistungen, Branchenfokus, Standorte, Kunden, Nachhaltigkeit, Karriere, Arbeitskultur, Influencer Relations, Generative KI und GEO, Personal Branding, Gesundheitskommunikation, Web3-Kommunikation, Kontaktaufnahme, Podcast, Netzwerk, Büro und Arbeitsumgebung, Newsletter, Vielfalt und Inklusion, Remote Work, Adresse, Öffnungszeiten Keine Dokumente | F12: FAQ-Themen aus dem Konfigurationsexport; keine Prüfung von Antwortinhalten. | G12: Breites Callback-Playbook „Anliegen aufnehmen“ vorhanden; ausgeschlossen. Negativlabel bezieht sich nur auf Ziel-Skills.
B15: Prüfregeln
B17: Prüfebene | C17: Skill-Auswahl und Werkzeugaktivierung prüfen, nicht Antwortkorrektheit, echte Buchungen oder erfolgreiche Telefonverbindungen.
B18: Skill-IDs | C18: Die technischen Werte calendar, knowledge-base, forwarding und none bleiben unverändert. Spalten und Erläuterungen sind deutsch.
B19: Wissensdatenbank | C19: Beim ersten Suchbedarf faq_search bzw. search_documents gemäß Erwartung. ODER bedeutet: Mindestens einer der genannten Suchwege ist akzeptabel.
B20: Kalender | C20: load_skill für calendar ist das Auswahlziel. Ein Abruf von get_user_info, get_event_types oder get_available_slots belegt den Einstieg in den Kalenderablauf.
B21: Kalender-Rückfragen | C21: Fehlende Terminart oder Zeit darf zuerst erfragt werden. Ein einzelner Nutzersatz reicht nicht immer für einen unmittelbaren Fachwerkzeugaufruf. Skill-Auswahl separat auswerten.
B22: Kalender-Abschluss | C22: transform_relative_date_to_iso darf bei relativen Daten folgen. create_booking ist erst nach vollständigen Angaben und Bestätigung zulässig und für diese Auswahltests nicht erforderlich.
B23: Nicht freigegebene Kalenderaktionen | C23: cancel_booking, reschedule_booking, get_booking, get_bookings und verify_booking_auth sind in den gelieferten Kalenderkonten keinem Skill freigegeben; keine positiven Aufruf-Erwartungen dafür.
B24: Weiterleitung | C24: load_skill für forwarding und select_playbook_topic mit dem genannten Playbook prüfen. get_phone_number_for_topic und transfer_to_phone_number sind spätere Ablaufwerkzeuge.
B25: Weiterleitungsbedingungen | C25: Bei Hausheld-Stadtwerke-Themen enthält der positive Testtext bereits Zustimmung. Bei Kundenservice notwendige Daten erfragen; Störungen laut Konfiguration ohne weitere Rückfragen weiterleiten.
B26: Negativfälle | C26: Keine Aktivierung von calendar, knowledge-base oder forwarding erwarten. Aufrufe außerhalb dieses Umfangs nicht als False Positive dieser drei Skills zählen. Kein universeller Null-Werkzeug-Test.
B27: Ähnlichkeit | C27: Je Bezugsgruppe zwei positive Äußerungen und ein thematisch verwandter Negativfall. Fallreihenfolge innerhalb der Gruppe variiert; Gruppen beim Aufteilen in Trainings-/Testdaten zusammenhalten.
B28: Schwierigkeit | C28: Redaktionelle Einschätzung: Leicht = klare kurze Absicht; Mittel = Kontext oder Rücknahme; Schwer = indirekte Absicht, Selbstkorrektur oder fremder Terminbezug. Keine gemessene Modellleistung.
... B31: Durchführung | C31: Pro Fall neuer Zustand im richtigen Konto. Nur Testäußerung als Nutzereingabe. Fehlende Parameter neutral ergänzen; erwartete Labels oder Werkzeugnamen dem Agenten nicht vorgeben.
